decision_graph/__init__.py
decision_graph/decision_tree/__init__.py
decision_graph/decision_tree/exc.py
decision_graph/decision_tree/capi/__init__.pxd
decision_graph/decision_tree/capi/__init__.py
decision_graph/decision_tree/capi/c_abc.cpython-314-x86_64-linux-gnu.so
decision_graph/decision_tree/capi/c_abc.pxd
decision_graph/decision_tree/capi/c_abc.pyi
decision_graph/decision_tree/capi/c_abc.pyx
decision_graph/decision_tree/capi/c_collection.cpython-314-x86_64-linux-gnu.so
decision_graph/decision_tree/capi/c_collection.pxd
decision_graph/decision_tree/capi/c_collection.pyi
decision_graph/decision_tree/capi/c_collection.pyx
decision_graph/decision_tree/capi/c_node.cpython-314-x86_64-linux-gnu.so
decision_graph/decision_tree/capi/c_node.pxd
decision_graph/decision_tree/capi/c_node.pyi
decision_graph/decision_tree/capi/c_node.pyx
decision_graph/decision_tree/native/__init__.py
decision_graph/decision_tree/native/abc.py
decision_graph/decision_tree/native/collection.py
decision_graph/decision_tree/native/node.py
decision_graph/decision_tree/webui/__init__.py
decision_graph/decision_tree/webui/app.py
decision_graph/decision_tree/webui/main.py
decision_graph/decision_tree/webui/static/d3.v7.min.js
decision_graph/decision_tree/webui/static/script.js
decision_graph/decision_tree/webui/static/style.css
decision_graph/decision_tree/webui/templates/index.html
decision_graph/decision_tree/webui/templates/offline.html
decision_graph/logic_group/__init__.py
decision_graph/logic_group/base.py
decision_graph/logic_group/pending_request.py
pydecisiongraph-0.2.9.dist-info/METADATA
pydecisiongraph-0.2.9.dist-info/WHEEL
pydecisiongraph-0.2.9.dist-info/top_level.txt
pydecisiongraph-0.2.9.dist-info/RECORD
pydecisiongraph-0.2.9.dist-info/licenses/LICENSE
