Metadata-Version: 2.4
Name: PyDecisionGraph
Version: 0.2.9
Summary: A rule-based decision tree implementation for Python
Home-page: https://github.com/BolunHan/PyDecisionGraph
Author: Han Bolun
Author-email: Han Bolun <Bolun.Han@outlook.com>
License-Expression: MPL-2.0
Project-URL: Homepage, https://github.com/BolunHan/PyDecisionGraph
Project-URL: Repository, https://github.com/BolunHan/PyDecisionGraph
Project-URL: Issues, https://github.com/BolunHan/PyDecisionGraph/issues
Keywords: decision tree,decision graph,rules,cython
Classifier: Programming Language :: Python :: 3
Classifier: Programming Language :: Python :: 3.12
Classifier: Operating System :: OS Independent
Requires-Python: >=3.12
License-File: LICENSE
Provides-Extra: visualization
Requires-Dist: flask; extra == "visualization"
Requires-Dist: jinja2; extra == "visualization"
Dynamic: license-file
